MANIFEST.in
README.md
setup.cfg
setup.py
gpapi/__init__.py
gpapi/config.py
gpapi/device.properties
gpapi/googleplay.py
gpapi/utils.py
test/test.py
zoro_gpapi.egg-info/PKG-INFO
zoro_gpapi.egg-info/SOURCES.txt
zoro_gpapi.egg-info/dependency_links.txt
zoro_gpapi.egg-info/requires.txt
zoro_gpapi.egg-info/top_level.txt